unirules/__init__.py
unirules/core/__init__.py
unirules/core/conditions.py
unirules/core/domains.py
unirules/core/fields.py
unirules/core/rules.py
unirules/domains/__init__.py
unirules/domains/common/__init__.py
unirules/domains/common/conditions.py
unirules/domains/discrete/__init__.py
unirules/domains/discrete/conditions.py
unirules/domains/discrete/domain.py
unirules/domains/discrete/field.py
unirules/domains/discrete/field_ref.py
unirules/domains/discrete/values.py
unirules/domains/interval/__init__.py
unirules/domains/interval/conditions.py
unirules/domains/interval/domain.py
unirules/domains/interval/field.py
unirules/domains/interval/field_ref.py
unirules/domains/interval/values.py
unirules/dsl.py
unirules/engines/__init__.py
unirules/engines/analyzer.py
unirules/engines/resolver.py
unirules/py.typed
unirules/ruleset_loader.py
unirules-0.1.1.dist-info/WHEEL
unirules-0.1.1.dist-info/METADATA
unirules-0.1.1.dist-info/RECORD
