Metadata-Version: 2.4
Name: unirules
Version: 0.1.1
Summary: unirules is a Python library for building declarative rule sets with a friendly DSL over discrete and interval domains, then turning them into runtime resolvers and analyzers that fit into your applications.
Keywords: rules,rule-engine,business-rules,decision-rules,decision-tree,declarative,symbolic-analysis
Author: Dmitry Shevchenko
Author-email: Dmitry Shevchenko <dmitry.e.shev@gmail.com>
License-Expression: MIT
Requires-Dist: typing-extensions>=4.15.0
Maintainer: Dmitry Shevchenko
Maintainer-email: Dmitry Shevchenko <dmitry.e.shev@gmail.com>
Requires-Python: >=3.9
Project-URL: Issue Tracker, https://github.com/de-shev/unirules/issues
Project-URL: Source Code, https://github.com/de-shev/unirules
